E4function.py
__init__.py
E4function-1.0.0.1.dist-info/METADATA
E4function-1.0.0.1.dist-info/WHEEL
E4function-1.0.0.1.dist-info/top_level.txt
E4function-1.0.0.1.dist-info/RECORD
